myapp/__init__.py
myapp/cli.py
passkey_cli-0.2.0.dist-info/licenses/LICENSE
passkey_cli-0.2.0.dist-info/METADATA
passkey_cli-0.2.0.dist-info/WHEEL
passkey_cli-0.2.0.dist-info/entry_points.txt
passkey_cli-0.2.0.dist-info/top_level.txt
passkey_cli-0.2.0.dist-info/RECORD
