Metadata-Version: 2.4
Name: passkey-cli
Version: 0.2.0
Summary: A secure CLI password manager connected to MongoDB
Author-email: Med Ali Lahmer <dalilahmer1212@gmail.com>
License-Expression: MIT
Project-URL: Homepage, https://github.com/MedAliLahmer/passkey-cli
Project-URL: Repository, https://github.com/MedAliLahmer/passkey-cli
Project-URL: Issues, https://github.com/MedAliLahmer/passkey-cli/issues
Keywords: cli,security,encryption,mongodb,passwords
Classifier: Development Status :: 3 - Alpha
Classifier: Intended Audience :: Developers
Classifier: Programming Language :: Python :: 3
Classifier: Programming Language :: Python :: 3.9
Classifier: Programming Language :: Python :: 3.10
Classifier: Programming Language :: Python :: 3.11
Classifier: Programming Language :: Python :: 3.12
Requires-Python: >=3.9
License-File: LICENSE
Requires-Dist: typer[all]>=0.9.0
Requires-Dist: pymongo>=4.0.0
Requires-Dist: cryptography>=40.0.0
Requires-Dist: keyring>=24.0.0
Dynamic: license-file
